revtok/__init__.py
revtok/subwords.py
revtok/tokenizer.py
revtok-0.0.3.dist-info/METADATA
revtok-0.0.3.dist-info/RECORD
revtok-0.0.3.dist-info/WHEEL
revtok-0.0.3.dist-info/top_level.txt
test/__init__.py
